django_quill/__init__.py
django_quill/config.py
django_quill/fields.py
django_quill/forms.py
django_quill/quill.py
django_quill/static/django_quill/django_quill.css
django_quill/static/django_quill/django_quill.js
django_quill/templates/django_quill/media.html
django_quill/templates/django_quill/widget.html
django_quill/widgets.py
django_quill_editor_ng-1.0.0.dist-info/LICENSE
django_quill_editor_ng-1.0.0.dist-info/WHEEL
django_quill_editor_ng-1.0.0.dist-info/METADATA
django_quill_editor_ng-1.0.0.dist-info/RECORD
